opencerebro/orchestrators/mcp/__init__.py
opencerebro_orchestrator_mcp-0.1.3.dist-info/METADATA
opencerebro_orchestrator_mcp-0.1.3.dist-info/WHEEL
opencerebro_orchestrator_mcp-0.1.3.dist-info/RECORD
